jota_os/__init__.py
jota_os/ai.py
jota_os/network.py
jota_os/nfs.py
jota_os/processes.py
jota_os/shell.py
jota_os-0.1.0.dist-info/LICENSE
jota_os-0.1.0.dist-info/METADATA
jota_os-0.1.0.dist-info/WHEEL
jota_os-0.1.0.dist-info/RECORD
