Metadata-Version: 2.1
Name: jota-os
Version: 0.1.0
Summary: 
Author: mrjohnnyrocha
Author-email: joaorocha619@gmail.com
Requires-Python: >=3.10,<4.0
Classifier: Programming Language :: Python :: 3
Classifier: Programming Language :: Python :: 3.10
Classifier: Programming Language :: Python :: 3.11
Classifier: Programming Language :: Python :: 3.12
Requires-Dist: torch (>=2.3.0,<3.0.0)
Requires-Dist: transformers (>=4.41.0,<5.0.0)
